repoload/__init__.py
repoload/__main__.py
repoload/repoload.py
repoload-0.2.dist-info/COPYING
repoload-0.2.dist-info/METADATA
repoload-0.2.dist-info/WHEEL
repoload-0.2.dist-info/entry_points.txt
repoload-0.2.dist-info/top_level.txt
repoload-0.2.dist-info/RECORD
