Metadata-Version: 2.1
Name: repoload
Version: 0.2
Summary: Repoload - a change request download tool.
Home-page: https://github.com/lengfeld/repoload
Author: Stefan Lengfeld, David Zerulla
Author-email: contact@stefanchrist.eu, ddaze@outlook.de
License: MIT
Keywords: repoload repo gerrit
Platform: any
Classifier: Programming Language :: Python :: 3
Classifier: License :: OSI Approved :: MIT License
Classifier: Operating System :: OS Independent
Requires-Python: >=3.5
